leangle/__init__.py
leangle/chalice_patches.py
leangle/describe.py
leangle/leangle.py
leangle-0.2.2.dist-info/DESCRIPTION.rst
leangle-0.2.2.dist-info/METADATA
leangle-0.2.2.dist-info/RECORD
leangle-0.2.2.dist-info/WHEEL
leangle-0.2.2.dist-info/metadata.json
leangle-0.2.2.dist-info/top_level.txt
