Metadata-Version: 2.0
Name: leangle
Version: 0.2.2
Summary: Add response descriptions to chalice
Home-page: https://github.com/jsfehler/leangle
Author: Joshua Fehler
License: GNU General Public License v3.0
Platform: UNKNOWN
Classifier: Programming Language :: Python :: 3.6
Classifier: Programming Language :: Python :: 3.7
Classifier: Programming Language :: Python :: 3.8
Provides-Extra: chalice
Requires-Dist: marshmallow-jsonschema
Provides-Extra: chalice
Requires-Dist: chalice (==1.13.0); extra == 'chalice'
